pyMultiSerial/__init__.py
pyMultiSerial-1.1.1.dist-info/LICENSE
pyMultiSerial-1.1.1.dist-info/METADATA
pyMultiSerial-1.1.1.dist-info/WHEEL
pyMultiSerial-1.1.1.dist-info/top_level.txt
pyMultiSerial-1.1.1.dist-info/RECORD
