Metadata-Version: 2.1
Name: pyMultiSerial
Version: 1.1.1
Summary: A Python module for simultaneous communication with multiple serial ports, based on pyserial module
Home-page: https://github.com/SunitRaut/pyMultiSerial
Author: Sunit Raut
Author-email: svraut29@gmail.com
Project-URL: Bug Tracker, https://github.com/SunitRaut/pyMultiSerial/issues
Classifier: Programming Language :: Python :: 3
Classifier: License :: OSI Approved :: GNU General Public License v3 (GPLv3)
Classifier: Operating System :: OS Independent
Requires-Python: >=3.0
License-File: LICENSE
Requires-Dist: pyserial
